LICENSE
MANIFEST.in
README.rst
pyproject.toml
setup.cfg
setup.py
django_t2020_polls.egg-info/PKG-INFO
django_t2020_polls.egg-info/SOURCES.txt
django_t2020_polls.egg-info/dependency_links.txt
django_t2020_polls.egg-info/requires.txt
django_t2020_polls.egg-info/top_level.txt
t2020_polls/__init__.py
t2020_polls/admin.py
t2020_polls/apps.py
t2020_polls/models.py
t2020_polls/tests.py
t2020_polls/urls.py
t2020_polls/views.py
t2020_polls/migrations/0001_initial.py
t2020_polls/migrations/__init__.py
t2020_polls/static/t2020_polls/style.css
t2020_polls/static/t2020_polls/images/4070tis.jpeg
t2020_polls/templates/t2020_polls/detail.html
t2020_polls/templates/t2020_polls/index.html
t2020_polls/templates/t2020_polls/results.html